HDL/Register_Counters/Universal_Shift_Register_4_beh.v
// Behavioral description of a 4-bit universal shift register
// Fig. 6.7and Table 6.3 
module Shift_Register_4_beh (
	output reg [3: 0] A_par, // Register output
	input [3: 0] I_par, // Parallel input
	input s1, s0, // Select inputs
	 MSB_in, LSB_in, // Serial inputs
	 CLK, Clear_b // Clock and Clear
	);
	
	always @ ( posedge CLK, negedge Clear_b) 
	if (Clear_b == 0) 
		A_par <= 4'b0000;
	else
	 	case ({s1, s0})
		 	2'b00: A_par <= A_par; // No change
			2'b01: A_par <= {MSB_in, A_par[3: 1]}; // Shift right
			2'b10: A_par <= {A_par[2: 0], LSB_in}; // Shift left
			2'b11: A_par <= I_par; // Parallel load of input
	    endcase
endmodule


module t_Shift_Register_4_beh;
	wire [3:0] A_par;
	wire[1:0]state;
	reg [3:0] I_par;
 	reg s1,s0, MSB_in, LSB_in, CLK, Clear_b;
	Shift_Register_4_beh UR (A_par,  I_par, s1, s0,	 MSB_in, LSB_in,  CLK, Clear_b);
	assign state= {s1,s0};
	initial 
		begin
		   $dumpfile("t_Shift_Register_4_beh.vcd");
	       $dumpvars(0, t_Shift_Register_4_beh);
		end
	initial #100 $finish;
	initial 
	  begin 
	  	  Clear_b = 1;
	      CLK = 0;
	      #5 Clear_b = 0;
	      #7 Clear_b = 1;
	      repeat (16)
	        #5 CLK = ~CLK;
      end
	initial 
	 begin
 		s1 = 0;
	    s0 = 0;
	    MSB_in = 1;
	    LSB_in = 0;
	    I_par =  4'b1010;
		#10 s0 = 1;
		#30 s1 = 1;
		#40 s0 = 0;
	end
endmodule

HDL/Register_Counters/t_Shift_Register_4_beh.vcd
$date
	Tue Nov 26 01:52:14 2024
$end
$version
	Icarus Verilog
$end
$timescale
	1s
$end
$scope module t_Shift_Register_4_beh $end
$var wire 2 ! state [1:0] $end
$var wire 4 " A_par [3:0] $end
$var reg 1 # CLK $end
$var reg 1 $ Clear_b $end
$var reg 4 % I_par [3:0] $end
$var reg 1 & LSB_in $end
$var reg 1 ' MSB_in $end
$var reg 1 ( s0 $end
$var reg 1 ) s1 $end
$scope module UR $end
$var wire 1 # CLK $end
$var wire 1 $ Clear_b $end
$var wire 4 * I_par [3:0] $end
$var wire 1 & LSB_in $end
$var wire 1 ' MSB_in $end
$var wire 1 ( s0 $end
$var wire 1 ) s1 $end
$var reg 4 + A_par [3:0] $end
$upscope $end
$upscope $end
$enddefinitions $end
$comment Show the parameter values. $end
$dumpall
$end
#0
$dumpvars
bx +
b1010 *
0)
0(
1'
0&
b1010 %
1$
0#
bx "
b0 !
$end
#5
b0 "
b0 +
0$
#10
b1 !
1(
#12
1$
#17
b1000 "
b1000 +
1#
#22
0#
#27
b1100 "
b1100 +
1#
#32
0#
#37
b1110 "
b1110 +
1#
#40
b11 !
1)
#42
0#
#47
b1010 "
b1010 +
1#
#52
0#
#57
1#
#62
0#
#67
1#
#72
0#
#77
1#
#80
b10 !
0(
#82
0#
#87
b100 "
b100 +
1#
