mux/demux81.v
module demux1to2(o0, o1, i, s);
  output reg o0, o1;
  input i, s;

  always @(*) begin
    if (s == 1'b0) begin
      o0 = i;
      o1 = 0;
    end else begin
      o0 = 0;
      o1 = i;
    end
  end
endmodule

module demux1to2__(o0, o1, i, s);
  output o0, o1;
  input i, s;

  assign o0 = i & ~s; // Output 0 is active when `s` is 0
  assign o1 = i & s;  // Output 1 is active when `s` is 1
endmodule


module demux1to8(out, i, s);
  output [7:0] out;  // 8 output lines
  input i;           // Input signal
  input [2:0] s;     // 3-bit select signal

  wire w0, w1;       // Intermediate wires

  // First layer: Split input using 1-to-2 demultiplexer
  demux1to2 d0(w0, w1, i, s[2]);

  // Second layer: Further split the two intermediate signals
  wire w2, w3, w4, w5;
  demux1to2 d1(w2, w3, w0, s[1]);
  demux1to2 d2(w4, w5, w1, s[1]);

  // Final layer: Split each signal to reach the final 8 outputs
  demux1to2 d3(out[0], out[1], w2, s[0]);
  demux1to2 d4(out[2], out[3], w3, s[0]);
  demux1to2 d5(out[4], out[5], w4, s[0]);
  demux1to2 d6(out[6], out[7], w5, s[0]);
endmodule



module testbench;
  reg i;
  reg [2:0] s;
  wire [7:0] out;

  demux1to8 uut(out, i, s);

  initial begin
    $dumpfile("demux1to8.vcd");
    $dumpvars(0, testbench);
    i = 1; s = 3'b000; #10; // Input to out[0]
    i = 1; s = 3'b001; #10; // Input to out[1]
    i = 1; s = 3'b010; #10; // Input to out[2]
    i = 1; s = 3'b011; #10; // Input to out[3]
    i = 1; s = 3'b100; #10; // Input to out[4]
    i = 1; s = 3'b101; #10; // Input to out[5]
    i = 1; s = 3'b110; #10; // Input to out[6]
    i = 1; s = 3'b111; #10; // Input to out[7]
    $finish;
  end

  initial begin
    $monitor("i = %b, s = %b, out = %b", i, s, out);
  end
endmodule

mux/demux1to8.vcd
$date
	Fri Nov 22 14:31:20 2024
$end
$version
	Icarus Verilog
$end
$timescale
	1s
$end
$scope module testbench $end
$var wire 8 ! out [7:0] $end
$var reg 1 " i $end
$var reg 3 # s [2:0] $end
$scope module uut $end
$var wire 1 " i $end
$var wire 3 $ s [2:0] $end
$var wire 1 % w5 $end
$var wire 1 & w4 $end
$var wire 1 ' w3 $end
$var wire 1 ( w2 $end
$var wire 1 ) w1 $end
$var wire 1 * w0 $end
$var wire 8 + out [7:0] $end
$scope module d0 $end
$var wire 1 " i $end
$var wire 1 , s $end
$var reg 1 * o0 $end
$var reg 1 ) o1 $end
$upscope $end
$scope module d1 $end
$var wire 1 * i $end
$var wire 1 - s $end
$var reg 1 ( o0 $end
$var reg 1 ' o1 $end
$upscope $end
$scope module d2 $end
$var wire 1 ) i $end
$var wire 1 . s $end
$var reg 1 & o0 $end
$var reg 1 % o1 $end
$upscope $end
$scope module d3 $end
$var wire 1 ( i $end
$var wire 1 / s $end
$var reg 1 0 o0 $end
$var reg 1 1 o1 $end
$upscope $end
$scope module d4 $end
$var wire 1 ' i $end
$var wire 1 2 s $end
$var reg 1 3 o0 $end
$var reg 1 4 o1 $end
$upscope $end
$scope module d5 $end
$var wire 1 & i $end
$var wire 1 5 s $end
$var reg 1 6 o0 $end
$var reg 1 7 o1 $end
$upscope $end
$scope module d6 $end
$var wire 1 % i $end
$var wire 1 8 s $end
$var reg 1 9 o0 $end
$var reg 1 : o1 $end
$upscope $end
$upscope $end
$upscope $end
$enddefinitions $end
$comment Show the parameter values. $end
$dumpall
$end
#0
$dumpvars
0:
09
08
07
06
05
04
03
02
01
10
0/
0.
0-
0,
b1 +
1*
0)
1(
0'
0&
0%
b0 $
b0 #
1"
b1 !
$end
#10
11
b10 !
b10 +
00
1/
12
15
18
b1 #
b1 $
#20
13
1'
0(
01
b100 !
b100 +
00
1-
1.
0/
02
05
08
b10 #
b10 $
#30
14
b1000 !
b1000 +
03
1/
12
15
18
b11 #
b11 $
#40
16
1&
00
1)
0*
0'
0(
04
b10000 !
b10000 +
03
1,
0-
0.
0/
02
05
08
b100 #
b100 $
#50
17
b100000 !
b100000 +
06
1/
12
15
18
b101 #
b101 $
#60
19
1%
0&
07
b1000000 !
b1000000 +
06
1-
1.
0/
02
05
08
b110 #
b110 $
#70
1:
b10000000 !
b10000000 +
09
1/
12
15
18
b111 #
b111 $
